pydantic_settings_azure_app_configuration/__init__.py
pydantic_settings_azure_app_configuration/py.typed
pydantic_settings_azure_app_configuration/source.py
pydantic_settings_azure_app_configuration-1.1.0.dist-info/WHEEL
pydantic_settings_azure_app_configuration-1.1.0.dist-info/METADATA
pydantic_settings_azure_app_configuration-1.1.0.dist-info/RECORD
