Metadata-Version: 2.3
Name: pydantic-settings-azure-app-configuration
Version: 1.1.0
Summary: Azure App Configuration setting source for pydantic-settings
Requires-Dist: pydantic>=2.8.2
Requires-Dist: pydantic-settings>=2.3.4
Requires-Dist: azure-appconfiguration>=1.6.0
Requires-Dist: azure-keyvault-secrets>=4.8.0
Requires-Dist: azure-identity>=1.17.1
Requires-Python: >=3.11
Project-URL: Documentation, https://github.com/AndreuCodina/pydantic-settings-azure-app-configuration
Project-URL: Repository, https://github.com/AndreuCodina/pydantic-settings-azure-app-configuration
